poseidon_module/__init__.py
poseidon_module/skeleton.py
poseidon_module/core/__init__.py
poseidon_module/core/const.py
poseidon_module/core/decorators.py
poseidon_module/core/globals.py
poseidon_module/core/logger.py
poseidon_module/core/poseidon.py
poseidon_module/utils/__init__.py
poseidon_module/utils/_codec.py
poseidon_module/utils/_device.py
poseidon_module/utils/_registry.py
poseidon_module/utils/_relay.py
poseidon_module/utils/_reorder.py
poseidon_module/utils/_shell.py
poseidon_module/utils/atb.py
poseidon_module/utils/comm.py
poseidon_module/utils/device.py
poseidon_module/utils/dingtalk.py
poseidon_module/utils/http_client.py
poseidon_module/utils/outlook.py
poseidon_module/utils/tz.py
poseidon_module/utils/uart.py
poseidon_module/utils/wlan.py
Poseidon_module-0.1.1.dist-info/LICENSE.txt
Poseidon_module-0.1.1.dist-info/METADATA
Poseidon_module-0.1.1.dist-info/WHEEL
Poseidon_module-0.1.1.dist-info/top_level.txt
Poseidon_module-0.1.1.dist-info/RECORD
