Metadata-Version: 2.1
Name: Poseidon-module
Version: 0.1.1
Summary: Add a short description here!
Home-page: https://github.com/pyscaffold/pyscaffold/
Author: duayong
Author-email: jack.du@fibocom.com
License: MIT
Project-URL: Documentation, https://pyscaffold.org/
Platform: any
Classifier: Development Status :: 4 - Beta
Classifier: Programming Language :: Python
License-File: LICENSE.txt
Requires-Dist: importlib-metadata ; python_version < "3.8"
Provides-Extra: testing
Requires-Dist: setuptools ; extra == 'testing'
Requires-Dist: pytest ; extra == 'testing'
Requires-Dist: pytest-cov ; extra == 'testing'
